LICENSE
MANIFEST.in
README
setup.py
bin/imgserve
imgserve/__init__.py
imgserve/__init__.pyc
imgserve/args.py
imgserve/args.pyc
imgserve/arial.ttf
imgserve/commands.py
imgserve/commands.pyc
imgserve/http.py
imgserve/http.pyc
imgserve/logfile.py
imgserve/logfile.pyc
imgserve/manager.py
imgserve/manager.pyc
imgserve/utils.py
imgserve/utils.pyc
imgserve/version.py
imgserve/version.pyc
imgserve/worker.py
imgserve/worker.pyc
imgserve.egg-info/PKG-INFO
imgserve.egg-info/SOURCES.txt
imgserve.egg-info/dependency_links.txt
imgserve.egg-info/requires.txt
imgserve.egg-info/top_level.txt
tests/http_tests.py
tests/http_tests.pyc
tests/servers.py
tests/servers.pyc
tests/data/1_example.gif
tests/data/1_example.jpeg
tests/data/1_example.jpg
tests/data/1_example.png
tests/data/1_example.svg
tests/data/actually_a_txt.gif
tests/data/actually_a_txt.jpeg
tests/data/actually_a_txt.jpg
tests/data/actually_a_txt.png
tests/data/too_small.gif
tests/data/too_small.jpeg
tests/data/too_small.jpg
tests/data/too_small.png