Metadata-Version: 1.0
Name: imgserve
Version: 0.2
Summary: Imgserve is a daemon program to provide common image processing service
Home-page: http://github.com/wuzhe/imgserve
Author: Wu Zhe
Author-email: wu@madk.org
License: GPL
Download-URL: http://pypi.python.org/pypi/imgserve
Keywords: image-processing daemon networking imgserve
Platform: UNKNOWN
Classifier: Development Status :: 3 - Alpha
Classifier: Environment :: Console
Classifier: Intended Audience :: Developers
Classifier: License :: OSI Approved :: GNU General Public License (GPL)
Classifier: Operating System :: OS Independent
Classifier: Programming Language :: Python
Classifier: Topic :: Internet
Classifier: Topic :: Multimedia :: Graphics :: Graphics Conversion
Classifier: Topic :: Utilities
